odoo/addons/sale_product_set_layout/README.rst
odoo/addons/sale_product_set_layout/__init__.py
odoo/addons/sale_product_set_layout/__manifest__.py
odoo/addons/sale_product_set_layout/demo/product_set.xml
odoo/addons/sale_product_set_layout/i18n/ca.po
odoo/addons/sale_product_set_layout/i18n/es.po
odoo/addons/sale_product_set_layout/i18n/fr.po
odoo/addons/sale_product_set_layout/i18n/hr.po
odoo/addons/sale_product_set_layout/i18n/pt.po
odoo/addons/sale_product_set_layout/i18n/sale_product_set_layout.pot
odoo/addons/sale_product_set_layout/i18n/sl.po
odoo/addons/sale_product_set_layout/models/__init__.py
odoo/addons/sale_product_set_layout/models/product_set_line.py
odoo/addons/sale_product_set_layout/readme/CONTRIBUTORS.rst
odoo/addons/sale_product_set_layout/readme/DESCRIPTION.rst
odoo/addons/sale_product_set_layout/static/description/icon.png
odoo/addons/sale_product_set_layout/static/description/icon.svg
odoo/addons/sale_product_set_layout/static/description/index.html
odoo/addons/sale_product_set_layout/tests/__init__.py
odoo/addons/sale_product_set_layout/tests/test_product_set_layout.py
odoo/addons/sale_product_set_layout/views/product_set.xml
odoo/addons/sale_product_set_layout/wizards/__init__.py
odoo/addons/sale_product_set_layout/wizards/product_set_add.py
odoo/addons/sale_product_set_layout/wizards/product_set_add.xml
odoo_addon_sale_product_set_layout-15.0.1.0.1.3.dist-info/METADATA
odoo_addon_sale_product_set_layout-15.0.1.0.1.3.dist-info/WHEEL
odoo_addon_sale_product_set_layout-15.0.1.0.1.3.dist-info/top_level.txt
odoo_addon_sale_product_set_layout-15.0.1.0.1.3.dist-info/RECORD
