Metadata-Version: 2.1
Name: odoo-addon-sale-product-set-layout
Version: 15.0.1.0.1.3
Summary: This module allows to add sections with product sets
Home-page: https://github.com/OCA/sale-workflow
Author: ACSONE SA/NV, Anybox, Odoo Community Association (OCA)
Author-email: support@odoo-community.org
License: AGPL-3
Platform: UNKNOWN
Classifier: Programming Language :: Python
Classifier: Framework :: Odoo
Classifier: Framework :: Odoo :: 15.0
Classifier: License :: OSI Approved :: GNU Affero General Public License v3
Requires-Python: >=3.8
Requires-Dist: odoo-addon-sale-product-set <15.1dev,>=15.0dev
Requires-Dist: odoo <15.1dev,>=15.0a
